{
  "nodes": [
    { "id": 1, "x": 75, "y": 75 },
    { "id": 2, "x": 150, "y": 75 },
    { "id": 3, "x": 225, "y": 75 },
    { "id": 4, "x": 300, "y": 75 },
    { "id": 5, "x": 375, "y": 75 },
    { "id": 6, "x": 75, "y": 150 },
    { "id": 7, "x": 150, "y": 150 },
    { "id": 8, "x": 225, "y": 150 },
    { "id": 9, "x": 300, "y": 150 },
    { "id": 10, "x": 375, "y": 150 },
    { "id": 11, "x": 75, "y": 225 },
    { "id": 12, "x": 150, "y": 225 },
    { "id": 13, "x": 225, "y": 225 },
    { "id": 14, "x": 300, "y": 225 },
    { "id": 15, "x": 375, "y": 225 },
    { "id": 16, "x": 75, "y": 300 },
    { "id": 17, "x": 150, "y": 300 },
    { "id": 18, "x": 225, "y": 300 },
    { "id": 19, "x": 300, "y": 300 },
    { "id": 20, "x": 375, "y": 300 },
    { "id": 21, "x": 75, "y": 375 },
    { "id": 22, "x": 150, "y": 375 },
    { "id": 23, "x": 225, "y": 375 },
    { "id": 24, "x": 300, "y": 375 },
    { "id": 25, "x": 375, "y": 375 }
  ],
  "edges": [
    { "from": 1, "to": 2 },
    { "from": 2, "to": 3 },
    { "from": 3, "to": 4 },
    { "from": 4, "to": 5 },
    { "from": 6, "to": 7 },
    { "from": 7, "to": 8 },
    { "from": 8, "to": 9 },
    { "from": 9, "to": 10 },
    { "from": 11, "to": 12 },
    { "from": 12, "to": 13 },
    { "from": 13, "to": 14 },
    { "from": 14, "to": 15 },
    { "from": 16, "to": 17 },
    { "from": 17, "to": 18 },
    { "from": 18, "to": 19 },
    { "from": 19, "to": 20 },
    { "from": 21, "to": 22 },
    { "from": 22, "to": 23 },
    { "from": 23, "to": 24 },
    { "from": 24, "to": 25 },
    { "from": 1, "to": 6 },
    { "from": 2, "to": 7 },
    { "from": 3, "to": 8 },
    { "from": 4, "to": 9 },
    { "from": 5, "to": 10 },
    { "from": 6, "to": 11 },
    { "from": 7, "to": 12 },
    { "from": 8, "to": 13 },
    { "from": 9, "to": 14 },
    { "from": 10, "to": 15 },
    { "from": 11, "to": 16 },
    { "from": 12, "to": 17 },
    { "from": 13, "to": 18 },
    { "from": 14, "to": 19 },
    { "from": 15, "to": 20 },
    { "from": 16, "to": 21 },
    { "from": 17, "to": 22 },
    { "from": 18, "to": 23 },
    { "from": 19, "to": 24 },
    { "from": 20, "to": 25 }
  ]
}